Metadata-Version: 2.4
Name: mseep-code-index-mcp
Version: 2.2.2
Summary: Code indexing and analysis tools for LLMs using MCP
Author-email: mseep <support@skydeck.ai>
License: MIT
Project-URL: Homepage, https://github.com/johnhuang316/code-index-mcp
Project-URL: Bug Tracker, https://github.com/johnhuang316/code-index-mcp/issues
Requires-Python: >=3.10
License-File: LICENSE
Requires-Dist: mcp>=0.3.0
Requires-Dist: watchdog>=3.0.0
Requires-Dist: tree-sitter>=0.20.0
Requires-Dist: tree-sitter-javascript>=0.20.0
Requires-Dist: tree-sitter-typescript>=0.20.0
Requires-Dist: tree-sitter-java>=0.20.0
Requires-Dist: tree-sitter-zig>=0.20.0
Requires-Dist: pathspec>=0.12.1
Requires-Dist: msgpack>=1.0.0
Dynamic: license-file
